NNetEn/LogNNet.py
NNetEn/NNetEn.py
NNetEn/__init__.py
NNetEn/database.py
NNetEn/Database/Base_0_balance_dot.txt
NNetEn/Database/SARS-CoV-2-RBV1.txt
NNetEn/Database/T-pattern-3.VM
NNetEn/Database/__init__.py
NNetEn/Database/t10k-images.idx3-ubyte
NNetEn/Database/t10k-labels.idx1-ubyte
NNetEn/Database/train-images.idx3-ubyte
NNetEn/Database/train-labels.idx1-ubyte
NNetEn-1.0.8.dist-info/LICENSE
NNetEn-1.0.8.dist-info/METADATA
NNetEn-1.0.8.dist-info/WHEEL
NNetEn-1.0.8.dist-info/top_level.txt
NNetEn-1.0.8.dist-info/RECORD
