Metadata-Version: 2.1
Name: NNetEn
Version: 1.0.8
Summary: Python Package for Neural Network Entropy (NNetEn) calculation
Home-page: https://github.com/izotov93/NNetEn
Author: Yuriy Izotov et al.
Author-email: izotov93@yandex.ru
Classifier: Development Status :: 5 - Production/Stable
Classifier: Programming Language :: Python :: 3.11
Classifier: Operating System :: OS Independent
Classifier: License :: OSI Approved :: BSD License
Requires-Python: >=3.8
License-File: LICENSE
Requires-Dist: numba >=0.57.1
